CONTRIBUTING.md
LICENSE.md
LICENSE.txt
MANIFEST.in
README.md
README.rst
install_requires.txt
requirements.txt
setup.py
tox.ini
dynamic_rest_client/__init__.py
dynamic_rest_client/client.py
dynamic_rest_client/exceptions.py
dynamic_rest_client/query.py
dynamic_rest_client/record.py
dynamic_rest_client/resource.py
dynamic_rest_client/utils.py
dynamic_rest_client.egg-info/PKG-INFO
dynamic_rest_client.egg-info/SOURCES.txt
dynamic_rest_client.egg-info/dependency_links.txt
dynamic_rest_client.egg-info/requires.txt
dynamic_rest_client.egg-info/top_level.txt
tests/test_client.py
tests/test_deepcopy.py