Metadata-Version: 2.1
Name: dynamic-rest-client
Version: 0.2.0
Summary: Python client for dynamic-rest with minimal dependencies
Home-page: http://github.com/AltSchool/dynamic-rest-client
License-File: LICENSE.md
License-File: LICENSE.txt
Requires-Dist: inflection>=0.3.1
Requires-Dist: requests
Requires-Dist: six
Requires-Dist: Django<5,>=3.2
